aiogram_tonconnect/__init__.py
aiogram_tonconnect/handlers.py
aiogram_tonconnect/manager.py
aiogram_tonconnect/middleware.py
aiogram_tonconnect/py.typed
aiogram_tonconnect/tonconnect/__init__.py
aiogram_tonconnect/tonconnect/callbacks.py
aiogram_tonconnect/tonconnect/models.py
aiogram_tonconnect/tonconnect/storage.py
aiogram_tonconnect/tonconnect/tasks.py
aiogram_tonconnect/utils/__init__.py
aiogram_tonconnect/utils/exceptions.py
aiogram_tonconnect/utils/keyboards.py
aiogram_tonconnect/utils/states.py
aiogram_tonconnect/utils/texts.py
aiogram_tonconnect/utils/qrcode/__init__.py
aiogram_tonconnect/utils/qrcode/generator.py
aiogram_tonconnect-0.15.0.dist-info/LICENSE
aiogram_tonconnect-0.15.0.dist-info/METADATA
aiogram_tonconnect-0.15.0.dist-info/WHEEL
aiogram_tonconnect-0.15.0.dist-info/top_level.txt
aiogram_tonconnect-0.15.0.dist-info/RECORD
