Metadata-Version: 2.1
Name: aiogram-tonconnect
Version: 0.15.0
Summary: aiogram-tonconnect is a user-friendly library for integrating TON Connect UI into aiogram-based Telegram bots.
Home-page: https://github.com/nessshon/aiogram-tonconnect/
Author: nessshon
License: MIT
Project-URL: Bot example, https://t.me/aiogramTONConnectBot/
Project-URL: Source Code, https://github.com/nessshon/aiogram-tonconnect/
Project-URL: Usage example, https://github.com/nessshon/aiogram-tonconnect/tree/main/example/
Keywords: aiogram,Telegram bots,TON blockchain,TON Connect,asynchronous,crypto,qrcode
Classifier: Development Status :: 4 - Beta
Classifier: Intended Audience :: Developers
Classifier: Topic :: Software Development :: Libraries :: Python Modules
Classifier: Framework :: AsyncIO
Classifier: Environment :: Console
Classifier: Programming Language :: Python :: 3.10
Classifier: Programming Language :: Python :: 3.11
Classifier: Programming Language :: Python :: 3.12
Classifier: License :: OSI Approved :: MIT License
Classifier: Operating System :: OS Independent
Requires-Python: >=3.10
License-File: LICENSE
Requires-Dist: aiogram <=3.20.0,>=3.0.0
Requires-Dist: cachetools >=5.3.0
Requires-Dist: pillow >=10.0.0
Requires-Dist: qrcode-styled >=0.2.2
Requires-Dist: redis >=5.0.5
Requires-Dist: tonutils >=0.4.5
